<?xml version="1.0" encoding="utf-8"?>
<eac-cpf xmlns="urn:isbn:1-931666-33-4"
         xmlns:xsi="http://www.w3.org/2001/XMLSchema-instance"
         xsi:schemaLocation="urn:isbn:1-931666-33-4 cpf.xsd">
   <control>
      <recordId>FRAN_NP_051552</recordId>
      <maintenanceStatus>new</maintenanceStatus>
      <maintenanceAgency>
         <agencyName>Archives nationales de France</agencyName>
      </maintenanceAgency>
      <languageDeclaration>
         <language languageCode="fre">Français</language>
         <script scriptCode="Latn"/>
      </languageDeclaration>
      <conventionDeclaration>
         <citation> Notice établie conformément à la norme ICA-ISAAR (CPF) 2004, aux normes ISO 8601 pour le système de normalisation des dates utilisé, ainsi que AFNOR NF Z44-061 juin 1986 Catalogage : forme et structure des vedettes noms de personne, des vedettes titres, des rubriques de classement et des titres forgés et NF Z 44-060, décembre 1996 Catalogue d'auteurs et d'anonymes – Forme et structure des vedettes de collectivités-auteurs. </citation>
      </conventionDeclaration>
      <localControl localType="niveau_de_detail">
         <term>Complète</term>
      </localControl>
      <maintenanceHistory>
         <maintenanceEvent>
            <eventType>created</eventType>
            <eventDateTime>2017-07-11</eventDateTime>
            <agentType>human</agentType>
            <agent>Constance DE VERGNETTE DE LAMOTTE</agent>
         </maintenanceEvent>
         <maintenanceEvent>
            <eventType>updated</eventType>
            <eventDateTime>2018-03-08</eventDateTime>
            <agentType>human</agentType>
            <agent>Isabelle ARISTIDE-HASTIR</agent>
         </maintenanceEvent>
      </maintenanceHistory>
      <sources>
         <source>
            <sourceEntry>Arch. nat., 184 AP : fonds Duroc, duc de Frioul</sourceEntry>
         </source>
         <source>
            <sourceEntry>http://data.bnf.fr/14529860/geraud_christophe_michel_duroc/</sourceEntry>
         </source>
         <source>
            <sourceEntry>https://fr.wikipedia.org/wiki/G%C3%A9raud_Christophe_Michel_Duroc</sourceEntry>
         </source>
         <source>
            <sourceEntry>Six (Georges), Dictionnaire biographique des généraux et amiraux français de la Révolution et de l'Empire (1792-1814), 1934, t. I, p. 410-411.</sourceEntry>
         </source>
         <source>
            <sourceEntry>Tulard (Jean) (dir.), Dictionnaire Napoléon, Fayard, 1999, vol. 1, p. 692-693.</sourceEntry>
         </source>
      </sources>
   </control>
   <cpfDescription>
      <identity>
         <entityId>ISNI 0000 0000 4337 4556</entityId>
         <entityType>person</entityType>
         <nameEntry localType="autorisée"
                    scriptCode="Latn"
                    xml:lang="fre"
                    xml:id="FRAN_agentName_051552-d4766e115">
            <part>Duroc, Géraud Christophe Michel (1772-1813)</part>
         </nameEntry>
         <nameEntry xml:id="FRAN_agentName_051552-d4766e121">
            <part>du Roc de Brion, Géraud Christophe Michel (1772-1813 ; chevalier de)</part>
         </nameEntry>
         <nameEntry xml:id="FRAN_agentName_051552-d4766e127">
            <part>Du Roc, Géraud Christophe Michel (1772-1813)</part>
         </nameEntry>
         <nameEntry xml:id="FRAN_agentName_051552-d4766e134">
            <part>Frioul, Géraud Christophe Michel Duroc (1772-1813 ; duc de)</part>
         </nameEntry>
      </identity>
      <description>
         <existDates>
            <dateRange>
               <fromDate standardDate="1772-10-25">25 octobre 1772</fromDate>
               <toDate standardDate="1813-05-23">23 mai 1813</toDate>
            </dateRange>
         </existDates>
         <places>
            <place xml:id="FRAN_place_051552-d4766e157">
               <placeRole>Lieu général</placeRole>
               <placeEntry localType="nomLieu" xml:id="FRAN_placeEntry_051552-d4766e162">Aboukir</placeEntry>
               <placeEntry localType="lieu"
                           vocabularySource="d3m08zmsonn-c08kv9i9ersn"
                           xml:id="FRAN_stdPlaceEntry_051552-d3m08zmsonn-c08kv9i9ersnd4766e165">Aboukir (Egypte)</placeEntry>
            </place>
            <place xml:id="FRAN_place_051552-d4766e169">
               <placeRole>Lieu général</placeRole>
               <placeEntry localType="nomLieu" xml:id="FRAN_placeEntry_051552-d4766e174">Bautzen</placeEntry>
               <placeEntry localType="lieu"
                           vocabularySource="d3ntxjxyl2-de3n2j7xfcc0"
                           xml:id="FRAN_stdPlaceEntry_051552-d3ntxjxyl2-de3n2j7xfcc0d4766e177">Allemagne</placeEntry>
            </place>
            <place xml:id="FRAN_place_051552-d4766e181">
               <placeRole>Lieu général</placeRole>
               <placeEntry localType="nomLieu" xml:id="FRAN_placeEntry_051552-d4766e186">Bayonne</placeEntry>
               <placeEntry localType="lieu"
                           vocabularySource="d3m08zhht0k--tkyaw3csd7xn"
                           xml:id="FRAN_stdPlaceEntry_051552-d3m08zhht0k--tkyaw3csd7xnd4766e189">Communes françaises</placeEntry>
            </place>
            <place xml:id="FRAN_place_051552-d4766e193">
               <placeRole>Lieu général</placeRole>
               <placeEntry localType="nomLieu" xml:id="FRAN_placeEntry_051552-d4766e198">Berlin</placeEntry>
               <placeEntry localType="lieu"
                           vocabularySource="d3ntxmncns-1jfxw04wm1vg7"
                           xml:id="FRAN_stdPlaceEntry_051552-d3ntxmncns-1jfxw04wm1vg7d4766e201">Berlin (Allemagne)</placeEntry>
            </place>
            <place xml:id="FRAN_place_051552-d4766e205">
               <placeRole>Lieu général</placeRole>
               <placeEntry localType="nomLieu" xml:id="FRAN_placeEntry_051552-d4766e210">Bâle</placeEntry>
               <placeEntry localType="lieu"
                           vocabularySource="d3m08yxfnl1--1brzoz107kair"
                           xml:id="FRAN_stdPlaceEntry_051552-d3m08yxfnl1--1brzoz107kaird4766e213">Bâle (Suisse)</placeEntry>
            </place>
            <place xml:id="FRAN_place_051552-d4766e218">
               <placeRole>Lieu général</placeRole>
               <placeEntry localType="nomLieu" xml:id="FRAN_placeEntry_051552-d4766e223">Posen</placeEntry>
               <placeEntry localType="lieu"
                           vocabularySource="d3m08zxausk-8s99isqo4fr"
                           xml:id="FRAN_stdPlaceEntry_051552-d3m08zxausk-8s99isqo4frd4766e226">Poznan (Pologne)</placeEntry>
            </place>
            <place xml:id="FRAN_place_051552-d4766e230">
               <placeRole>Lieu général</placeRole>
               <placeEntry localType="nomLieu" xml:id="FRAN_placeEntry_051552-d4766e235">Russie</placeEntry>
               <placeEntry localType="lieu"
                           vocabularySource="d3ntxlhlzu--xk25nxgg86yz"
                           xml:id="FRAN_stdPlaceEntry_051552-d3ntxlhlzu--xk25nxgg86yzd4766e238">Russie</placeEntry>
            </place>
            <place xml:id="FRAN_place_051552-d4766e242">
               <placeRole>Lieu général</placeRole>
               <placeEntry localType="nomLieu" xml:id="FRAN_placeEntry_051552-d4766e247">Pont-à-Mousson</placeEntry>
               <placeEntry localType="lieu"
                           vocabularySource="d3ntl8476f--5w2gkokeedfd"
                           xml:id="FRAN_stdPlaceEntry_051552-d3ntl8476f--5w2gkokeedfdd4766e250">Pont-à-Mousson (Meurthe-et-Moselle)</placeEntry>
               <dateRange>
                  <fromDate standardDate="1772-10-25">25 octobre 1772</fromDate>
                  <toDate standardDate="1789-12-31">1789</toDate>
               </dateRange>
            </place>
         </places>
         <occupations>
            <occupation xml:id="FRAN_occupation_051552-d4766e266">
               <term vocabularySource="d699msj9l7t-1gb5a09kkzrmp">sénateur</term>
            </occupation>
            <occupation xml:id="FRAN_occupation_051552-d4766e272">
               <term vocabularySource="d3m0bl7an80--1igec9t065fzk">grand officier de la maison du roi (Ancien Régime)</term>
               <dateRange>
                  <fromDate standardDate="1804-01-01">1804</fromDate>
                  <toDate standardDate="1813-05-22">22 mai 1813</toDate>
               </dateRange>
               <descriptiveNote>
                  <p> Grand officier puis grand maréchal du palais de l'Empereur. </p>
               </descriptiveNote>
            </occupation>
            <occupation xml:id="FRAN_occupation_051552-d4766e293">
               <term vocabularySource="d699msk3a25-1xs3m641rhiyg">officier général</term>
               <dateRange>
                  <fromDate standardDate="1801-01-01">1801</fromDate>
                  <toDate standardDate="1813-05-22">22 mai 1813</toDate>
               </dateRange>
               <descriptiveNote>
                  <p> Général de brigade en 1801 puis général de division en 1803. Grand maréchal du palais. </p>
               </descriptiveNote>
            </occupation>
         </occupations>
         <biogHist>
            <p>Cadet gentilhomme à l’Ecole militaire de Pont-à-Mousson, Géraud Christophe Michel Duroc (1772-1813) démissionne le 22 juillet 1792. Il émigre puis revient en France.</p>
            <p>Lieutenant en second le 1 er juin 1793, il fait les campagnes de la Révolution comme aide de camp du général Lespinasse. Il se signale en Italie, devient aide de camp de Bonaparte qu’il accompagne en Egypte. Grièvement blessé à Aboukir, le 25 juillet 1799, il le seconde lors du coup d’Etat de brumaire. Promu général de brigade, il est chargé de missions diplomatiques à la cour de Berlin en novembre 1799, puis à Bâle en février 1800, à Vienne, à Stockholm et à Saint-Pétersbourg. Il est nommé général de brigade le 13 octobre 1801, gouverneur des Tuileries le 20 novembre, général de division le 27 août 1803. Il sert au camp de Boulogne de 1803 à 1805. Entre-temps, il était nommé officier puis grand maréchal du palais. Il participe aux campagnes d’Autriche, de Prusse et de Pologne de 1805 à 1807.</p>
            <p>En mai 1802, il est créé duc de Frioul. Napoléon l’envoit pour négocier plusieurs traités (Posen, 1807, Bayonne, 1808). Il sert en Russie en 1812. Il est nommé sénateur, le 5 avril 1813. Il suit l’Empereur en Saxe mais il est mortellement blessé à la bataille de Bautzen en mai 1813.</p>
         </biogHist>
      </description>
      <relations>
         <cpfRelation xmlns:xlink="http://www.w3.org/1999/xlink"
                      cpfRelationType="associative"
                      xlink:href="FRAN_NP_051171"
                      xlink:type="simple"
                      xml:id="FRAN_relation_051552-d4766e330">
            <relationEntry>Napoléon Ier (empereur des Français ; 1769-1821)</relationEntry>
            <dateRange>
               <fromDate standardDate="1796-01-01">1796</fromDate>
               <toDate standardDate="1813-05-23">23 mai 1813</toDate>
            </dateRange>
         </cpfRelation>
         <cpfRelation xmlns:xlink="http://www.w3.org/1999/xlink"
                      cpfRelationType="temporal-later"
                      xlink:href="FRAN_NP_050149"
                      xlink:type="simple"
                      xml:id="FRAN_relation_051552-d4766e345">
            <relationEntry>Bertrand, Henri-Gatien (1773-1844)</relationEntry>
            <dateRange>
               <fromDate standardDate="1813-05-22">22 mai 1813</fromDate>
            </dateRange>
            <descriptiveNote>
               <p>
     Le général Bertrand prend la suite de Duroc en tant que grand-maréchal du Palais.
    </p>
            </descriptiveNote>
         </cpfRelation>
         <cpfRelation xmlns:xlink="http://www.w3.org/1999/xlink"
                      cpfRelationType="identity"
                      xlink:href="http://catalogue.bnf.fr/ark:/12148/cb145298607"
                      xlink:type="simple"
                      xml:id="FRAN_relation_051552-d4766e363">
            <relationEntry>Duroc, Géraud Christophe Michel (1772-1813)</relationEntry>
            <dateRange>
               <fromDate standardDate="1772-10-25">25 octobre 1772</fromDate>
               <toDate standardDate="1813-05-23">23 mai 1813</toDate>
            </dateRange>
            <descriptiveNote>
               <p>Notice BnF</p>
            </descriptiveNote>
         </cpfRelation>
         <cpfRelation xmlns:xlink="http://www.w3.org/1999/xlink"
                      cpfRelationType="identity"
                      xlink:href="https://fr.wikipedia.org/wiki/G%C3%A9raud_Christophe_Michel_Duroc"
                      xlink:type="simple"
                      xml:id="FRAN_relation_051552-d4766e384">
            <relationEntry>Géraud Christophe Michel Duroc</relationEntry>
            <dateRange>
               <fromDate standardDate="1772-10-25">25 octobre 1772</fromDate>
               <toDate standardDate="1813-05-23">23 mai 1813</toDate>
            </dateRange>
            <descriptiveNote>
               <p>Notice Wikipédia</p>
            </descriptiveNote>
         </cpfRelation>
         <resourceRelation xmlns:xlink="http://www.w3.org/1999/xlink"
                           resourceRelationType="creatorOf"
                           xlink:href="FRAN_IR_003827"
                           xlink:type="simple"
                           xml:id="FRAN_relation_051552-d4766e405">
            <relationEntry localType="archival">Archives de la Secrétairerie d'État impériale : administration de la Guerre (1800-1814)</relationEntry>
         </resourceRelation>
         <resourceRelation xmlns:xlink="http://www.w3.org/1999/xlink"
                           resourceRelationType="creatorOf"
                           xlink:href="FRAN_IR_003828"
                           xlink:type="simple"
                           xml:id="FRAN_relation_051552-d4766e412">
            <relationEntry localType="archival">Archives du Consulat et de la Secrétairerie d'État impériale : Relations extérieures (an VIII-1815)</relationEntry>
         </resourceRelation>
         <resourceRelation xmlns:xlink="http://www.w3.org/1999/xlink"
                           resourceRelationType="creatorOf"
                           xlink:href="FRAN_IR_025003"
                           xlink:type="simple"
                           xml:id="FRAN_relation_051552-d4766e418">
            <relationEntry localType="archival">Archives du dépôt des Fêtes et du Garde-Meuble (Révolution, Directoire et Premier Empire)</relationEntry>
         </resourceRelation>
         <resourceRelation xmlns:xlink="http://www.w3.org/1999/xlink"
                           resourceRelationType="creatorOf"
                           xlink:href="FRAN_IR_004095"
                           xlink:type="simple"
                           xml:id="FRAN_relation_051552-d4766e424">
            <relationEntry localType="archival">Fonds de la Secrétairerie d'Etat impériale : Etats dépendants (an VI-1814)</relationEntry>
         </resourceRelation>
         <resourceRelation xmlns:xlink="http://www.w3.org/1999/xlink"
                           resourceRelationType="creatorOf"
                           xlink:href="FRAN_IR_001657"
                           xlink:type="simple"
                           xml:id="FRAN_relation_051552-d4766e430">
            <relationEntry localType="archival">Maison de l’Empereur. Administration de l’intendance générale (an X-1815)</relationEntry>
         </resourceRelation>
         <resourceRelation xmlns:xlink="http://www.w3.org/1999/xlink"
                           resourceRelationType="creatorOf"
                           xlink:href="FRAN_IR_054358"
                           xlink:type="simple"
                           xml:id="FRAN_relation_051552-d4766e436">
            <relationEntry localType="archival">Papiers du général Duroc, duc de Frioul (1802-1813).</relationEntry>
         </resourceRelation>
         <resourceRelation xmlns:xlink="http://www.w3.org/1999/xlink"
                           resourceRelationType="creatorOf"
                           xlink:href="FRAN_IR_003371"
                           xlink:type="simple"
                           xml:id="FRAN_relation_051552-d4766e442">
            <relationEntry localType="archival">Sénat conservateur et Chambre des pairs impériale (1799-1815)</relationEntry>
         </resourceRelation>
      </relations>
   </cpfDescription>
</eac-cpf>
