<eac-cpf xmlns="urn:isbn:1-931666-33-4"
         xmlns:xsi="http://www.w3.org/2001/XMLSchema-instance"
         xsi:schemaLocation="urn:isbn:1-931666-33-4 cpf.xsd">
   <control>
      <recordId>FRAN_NP_011888</recordId>
      <otherRecordId localType="Ancien_identifiant">FRDAFANCH00MC_NANOTAIRE01723</otherRecordId>
      <maintenanceStatus>revised</maintenanceStatus>
      <maintenanceAgency>
         <agencyName>Archives nationales de France</agencyName>
      </maintenanceAgency>
      <languageDeclaration>
         <language languageCode="fre">Français</language>
         <script scriptCode="Latn"/>
      </languageDeclaration>
      <conventionDeclaration>
         <citation>Notice établie conformément à la norme ICA-ISAAR (CPF) 2004, aux normes ISO 8601 pour le système de normalisation des dates utilisé, ainsi que AFNOR NF Z 44-061, juin 1986. Catalogage : forme et structure des vedettes noms de personne, des vedettes titres, des rubriques de classement et des titres forgés.</citation>
      </conventionDeclaration>
      <localControl localType="niveau_de_detail">
         <term>Moyenne</term>
      </localControl>
      <maintenanceHistory>
         <maintenanceEvent>
            <eventType>derived</eventType>
            <eventDateTime>2013-04-23</eventDateTime>
            <agentType>machine</agentType>
            <agent>Migration ETANOT</agent>
         </maintenanceEvent>
         <maintenanceEvent>
            <eventType>revised</eventType>
            <eventDateTime>2014-04-02</eventDateTime>
            <agentType>human</agentType>
            <agent>Florence CLAVAUD</agent>
            <eventDescription>F. Clavaud, 2 avril 2014 : révision des liens IR</eventDescription>
         </maintenanceEvent>
      </maintenanceHistory>
      <sources>
         <source>
            <descriptiveNote>
               <p>ET/XLVII/266, 12 décembre 1772, vente par Jacques Miller de son office à Jean-Nicolas Giard, son principal clerc</p>
            </descriptiveNote>
         </source>
      </sources>
   </control>
   <cpfDescription>
      <identity>
         <entityType>person</entityType>
         <nameEntry localType="autorisée" scriptCode="Latn" xml:lang="fre">
            <part>Giard, Jean-Nicolas</part>
         </nameEntry>
      </identity>
      <description>
         <existDates>
            <dateRange>
               <fromDate standardDate="1771-12-20">20 décembre 1771</fromDate>
               <toDate standardDate="1794-02-01">1er février 1794</toDate>
            </dateRange>
            <descriptiveNote>
               <p>Les dates d'existence de la personne ne sont pas connues et sont évaluées d'après les dates d'exercice en tant que notaire</p>
            </descriptiveNote>
         </existDates>
         <places>
            <place>
               <placeRole>Lieu de Paris</placeRole>
               <placeEntry localType="paroisse" vocabularySource="d3nyvovxws-1r3061wzh7bqc">Saint-Etienne-du-Mont (paroisse)</placeEntry>
               <placeEntry localType="quartier" vocabularySource="d3nyvgqtes--1wrsaggwbjmzu">Saint-Benoît (quartier)</placeEntry>
               <placeEntry localType="voie" vocabularySource="d3nzc3mtjw-1ba0ccyicv9sx">Montagne-Sainte-Geneviève (rue de la)</placeEntry>
               <placeEntry localType="nomLieu">rue de la Montagne Sainte Geneviève</placeEntry>
            </place>
         </places>
         <functions>
            <function>
               <term vocabularySource="d3nyui3o8w--11y7jgy8q3wnt">notaire à Paris</term>
               <dateRange>
                  <fromDate standardDate="1771-12-20">20 décembre 1771</fromDate>
                  <toDate standardDate="1794-02-01">1er février 1794</toDate>
               </dateRange>
            </function>
         </functions>
         <biogHist>
            <p>D'abord principal clerc de Jacques Miller, dont il rachète l'office.</p>
            <p>Destitué.</p>
            <p>Réintégré, il laissa son office à BOILLEAU</p>
         </biogHist>
      </description>
      <relations>
         <cpfRelation xmlns:xlink="http://www.w3.org/1999/xlink"
                      cpfRelationType="associative"
                      xlink:href="FRAN_NP_010145"
                      xlink:type="simple">
            <relationEntry>Etude notariale XVIII</relationEntry>
            <dateRange>
               <fromDate standardDate="1771-12-20">20 décembre 1771</fromDate>
               <toDate standardDate="1794-02-01">1er février 1794</toDate>
            </dateRange>
         </cpfRelation>
         <resourceRelation xmlns:xlink="http://www.w3.org/1999/xlink"
                           resourceRelationType="creatorOf"
                           xlink:href="FRAN_IR_041529"
                           xlink:type="simple">
            <relationEntry localType="archival">Minutes et répertoires du notaire Jean Nicolas GIARD, 19 décembre 1771 - 1er février 1794 (étude XVIII)</relationEntry>
         </resourceRelation>
         <resourceRelation xmlns:xlink="http://www.w3.org/1999/xlink"
                           resourceRelationType="creatorOf"
                           xlink:href="FRAN_IR_041549"
                           xlink:type="simple">
            <relationEntry localType="archival">Minutes et répertoires du notaire Jean Nicolas GIARD, 19 décembre 1771 - décembre 1780 (étude XVIII)</relationEntry>
         </resourceRelation>
         <resourceRelation xmlns:xlink="http://www.w3.org/1999/xlink"
                           resourceRelationType="creatorOf"
                           xlink:href="FRAN_IR_041551"
                           xlink:type="simple">
            <relationEntry localType="archival">Minutes et répertoires du notaire Jean Nicolas GIARD, janvier 1791 - 1er février 1794 (étude XVIII)</relationEntry>
         </resourceRelation>
         <resourceRelation xmlns:xlink="http://www.w3.org/1999/xlink"
                           resourceRelationType="creatorOf"
                           xlink:href="FRAN_IR_041550"
                           xlink:type="simple">
            <relationEntry localType="archival">Minutes et répertoires du notaire Jean Nicolas GIARD, janvier 1781 - décembre 1790 (étude XVIII)</relationEntry>
         </resourceRelation>
         <resourceRelation xmlns:xlink="http://www.w3.org/1999/xlink"
                           resourceRelationType="creatorOf"
                           xlink:href="FRAN_IR_052970"
                           xlink:type="simple">
            <relationEntry localType="archival">Images des répertoires du notaire Jean Nicolas Giard pour l'étude XVIII</relationEntry>
         </resourceRelation>
      </relations>
   </cpfDescription>
</eac-cpf>
